simplelayout/__init__.py
simplelayout/__main__.py
simplelayout/cli/__init__.py
simplelayout/cli/cli_generate.py
simplelayout/generator/__init__.py
simplelayout/generator/core.py
simplelayout/generator/utils.py
simplelayout_zhaoxiaoyu1995-0.1.dist-info/LICENSE
simplelayout_zhaoxiaoyu1995-0.1.dist-info/METADATA
simplelayout_zhaoxiaoyu1995-0.1.dist-info/WHEEL
simplelayout_zhaoxiaoyu1995-0.1.dist-info/entry_points.txt
simplelayout_zhaoxiaoyu1995-0.1.dist-info/top_level.txt
simplelayout_zhaoxiaoyu1995-0.1.dist-info/RECORD
