Metadata-Version: 2.1
Name: simplelayout-zhaoxiaoyu1995
Version: 0.1
Summary: The Simple Layout Generator
Home-page: UNKNOWN
Author: zhaoxiaoyu
Author-email: zhaoxiaoyu1995@foxmail.com
License: UNKNOWN
Platform: UNKNOWN
Classifier: Programming Language :: Python :: 3
Classifier: License :: OSI Approved :: MIT License
Classifier: Operating System :: OS Independent
Requires-Python: >=3.6
License-File: LICENSE
Requires-Dist: numpy
Requires-Dist: matplotlib
Requires-Dist: scipy
